cleverlab.py
common_pb2.py
loader.py
login_pb2.py
protocol.py
devices/__init__.py
devices/CL/__init__.py
devices/CL/cleverlab/__init__.py
devices/CL/cleverlab/ai/__init__.py
devices/CL/cleverlab/ai/cleverlab_display_pb2.py
devices/CL/cleverlab/ai/cleverlab_eye_pb2.py
devices/CL/cleverlab/ai/laboratory_note_maker_pb2.py
devices/CL/cleverlab/ai/laboratory_photo_manager_pb2.py
devices/CL/cleverlab/ai/system_enviroment_pb2.py
devices/CL/cleverlab/ai/test_temperature_pb2.py
devices/CL/cleverlab/ai/text_display_pb2.py
cleverlab-0.0.3.dist-info/LICENSE
cleverlab-0.0.3.dist-info/METADATA
cleverlab-0.0.3.dist-info/WHEEL
cleverlab-0.0.3.dist-info/top_level.txt
cleverlab-0.0.3.dist-info/RECORD
