Metadata-Version: 2.1
Name: cleverlab
Version: 0.0.3
Summary: A prototype SDK for using Cleverlab
Home-page: UNKNOWN
Author: Kai-Chun-Hsieh
Author-email: cognitive@ars.de
License: UNKNOWN
Platform: UNKNOWN
Classifier: Programming Language :: Python :: 3
Classifier: License :: OSI Approved :: GNU Affero General Public License v3
Classifier: Operating System :: OS Independent
